<?xml version="1.0"?>
<!DOCTYPE hibernate-mapping PUBLIC "-//Hibernate/Hibernate Mapping DTD 3.0//EN" "http://hibernate.sourceforge.net/hibernate-mapping-3.0.dtd">

<hibernate-mapping default-lazy="false" auto-import="false">
	<import class="com.mpwc.model.Worker" />
	<class name="com.mpwc.model.impl.WorkerImpl" table="tbl_mpwc_workers">
		<cache usage="read-write" />
		<id name="workerId" type="long">
			<generator class="sequence">
				<param name="sequence">seq_worker_workerid</param>
			</generator>
		</id>
		<property name="groupId" type="com.liferay.portal.dao.orm.hibernate.LongType" />
		<property name="companyId" type="com.liferay.portal.dao.orm.hibernate.LongType" />
		<property name="userId" type="com.liferay.portal.dao.orm.hibernate.LongType" />
		<property name="userName" type="com.liferay.portal.dao.orm.hibernate.StringType" />
		<property name="createDate" type="org.hibernate.type.TimestampType" />
		<property name="modifiedDate" type="org.hibernate.type.TimestampType" />
		<property name="nif" type="com.liferay.portal.dao.orm.hibernate.StringType" />
		<property name="name" type="com.liferay.portal.dao.orm.hibernate.StringType" />
		<property name="surname" type="com.liferay.portal.dao.orm.hibernate.StringType" />
		<property name="email" type="com.liferay.portal.dao.orm.hibernate.StringType" />
		<property name="phone" type="com.liferay.portal.dao.orm.hibernate.StringType" />
		<property name="comments" type="com.liferay.portal.dao.orm.hibernate.StringType" />
		<property name="status" type="com.liferay.portal.dao.orm.hibernate.IntegerType" />
	</class>
</hibernate-mapping>